pywe_card/__init__.py
pywe_card/pywecard.py
pywe_card-1.0.0.dist-info/METADATA
pywe_card-1.0.0.dist-info/WHEEL
pywe_card-1.0.0.dist-info/top_level.txt
pywe_card-1.0.0.dist-info/RECORD
